Metadata-Version: 1.0
Name: ionstruct
Version: 0.0.1
Summary: A Python package to generate visualizations of TEC measurements in the ionosphere.
Home-page: UNKNOWN
Author: Rahul Priyadarshan R
Author-email: rahulpriyadarshan19@gmail.com
License: UNKNOWN
Platform: UNKNOWN
